README.md
setup.py
heisenberg/__init__.py
heisenberg/core.py
heisenberg/datastructures.py
heisenberg/rest_client.py
heisenberg/shell.py
heisenberg/utils.py
heisenberg/actions/__init__.py
heisenberg/actions/attack.py
heisenberg/actions/char.py
heisenberg/actions/heist.py
heisenberg/actions/unit.py
heisenberg/actions/upgrade.py
heisenberg_drugwars.egg-info/PKG-INFO
heisenberg_drugwars.egg-info/SOURCES.txt
heisenberg_drugwars.egg-info/dependency_links.txt
heisenberg_drugwars.egg-info/entry_points.txt
heisenberg_drugwars.egg-info/requires.txt
heisenberg_drugwars.egg-info/top_level.txt