Metadata-Version: 1.0
Name: heisenberg-drugwars
Version: 0.1.1
Summary: A Python library to interact with the drugwars online game
Home-page: https://github.com/emre/heisenberg
Author: Emre Yilmaz
Author-email: mail@emreyilmaz.me
License: MIT
Platform: UNKNOWN
